droneframe/__init__.py
droneframe/cli.py
droneframe/droneframe.py
droneframe-0.1.1.dist-info/LICENSE
droneframe-0.1.1.dist-info/METADATA
droneframe-0.1.1.dist-info/WHEEL
droneframe-0.1.1.dist-info/entry_points.txt
droneframe-0.1.1.dist-info/top_level.txt
droneframe-0.1.1.dist-info/RECORD
